{
    "name": "存储网络",
    "icon": "storagenetwork:builder_remote",
    "category": "storage_category",
    "advancement": "minecraft:story/mine_diamond",
    "pages":[
        {
            "type":"text",
            "text":"        对于难顶科技模组的冒险家来说，简易存储网络无疑是一个超棒的存储模组！使用网络线缆和书合成存储网络指导手册，学习如何快速搭建你的存储网络。需要注意的是，由于会引起崩溃，网络远程收集器已进入黑名单。搭建时别忘了把小箱子都换成更多箱子的大箱子~"
        },
        {
            "type":"crafting",
            "recipe":"storagenetwork:network_book",
            "title":"存储网络指导手册"
        }
    ]
}